[
  {
    "text": "What does Able mean",
    "options": [
      "Not able to do something",
      "Having the skill, power or means to do something",
      "Very tired",
      "To sleep deeply"
    ],
    "answer": 1
  },
  {
    "text": "What does Big mean",
    "options": [
      "Very small",
      "Large in size",
      "Red in color",
      "Easy to carry"
    ],
    "answer": 1
  },
  {
    "text": "What does Cold mean",
    "options": [
      "Having a low temperature",
      "Very hot",
      "Making noise",
      "Sleeping"
    ],
    "answer": 0
  },
  {
    "text": "What does Dark mean",
    "options": [
      "Without light or little light",
      "Very bright",
      "Being loud",
      "Running fast"
    ],
    "answer": 0
  },
  {
    "text": "What does Easy mean",
    "options": [
      "Hard to do",
      "Simple or not difficult",
      "Always boring",
      "Very fast"
    ],
    "answer": 1
  },
  {
    "text": "What does Fast mean",
    "options": [
      "Moving quickly",
      "Moving slowly",
      "Standing still",
      "Sleeping deeply"
    ],
    "answer": 0
  },
  {
    "text": "What does Good mean",
    "options": [
      "Bad or unpleasant",
      "Right or satisfactory",
      "Ugly or scary",
      "Very loud"
    ],
    "answer": 1
  },
  {
    "text": "What does Happy mean",
    "options": [
      "Feeling joy",
      "Feeling tired",
      "Feeling sick",
      "Feeling cold"
    ],
    "answer": 0
  },
  {
    "text": "What does Hot mean",
    "options": [
      "Having a high temperature",
      "Very cold",
      "Very dark",
      "Very easy"
    ],
    "answer": 0
  },
  {
    "text": "What does Jump mean",
    "options": [
      "Move into the air using your legs",
      "Run slowly",
      "Sleep fast",
      "Shout loudly"
    ],
    "answer": 0
  },
  {
    "text": "What does Kind mean",
    "options": [
      "Nasty or mean",
      "Friendly and nice",
      "Very quiet",
      "Very fast"
    ],
    "answer": 1
  },
  {
    "text": "What does Large mean",
    "options": [
      "Small in size",
      "Big in size",
      "Very bright",
      "Very quiet"
    ],
    "answer": 1
  },
  {
    "text": "What does Light mean",
    "options": [
      "Not heavy",
      "Very dark",
      "Very cold",
      "Very heavy"
    ],
    "answer": 0
  },
  {
    "text": "What does Loud mean",
    "options": [
      "Making a lot of noise",
      "Very quiet",
      "Very fast",
      "Very slow"
    ],
    "answer": 0
  },
  {
    "text": "What does New mean",
    "options": [
      "Old and used",
      "Just made or discovered",
      "Very tired",
      "Very heavy"
    ],
    "answer": 1
  },
  {
    "text": "What does Old mean",
    "options": [
      "Young and new",
      "Having lived a long time",
      "Very bright",
      "Very fast"
    ],
    "answer": 1
  },
  {
    "text": "What does Quick mean",
    "options": [
      "Slow in speed",
      "Fast in movement or action",
      "Very tired",
      "Very happy"
    ],
    "answer": 1
  },
  {
    "text": "What does Quiet mean",
    "options": [
      "Making little or no noise",
      "Very loud",
      "Very bright",
      "Very fast"
    ],
    "answer": 0
  },
  {
    "text": "What does Rain mean",
    "options": [
      "Water that falls from clouds",
      "Snow",
      "Strong wind",
      "Very hot sun"
    ],
    "answer": 0
  },
  {
    "text": "What does Rest mean",
    "options": [
      "To stop work and relax",
      "To run quickly",
      "To jump high",
      "To swim fast"
    ],
    "answer": 0
  },
  {
    "text": "What does Safe mean",
    "options": [
      "Free from danger",
      "Very dangerous",
      "Very dark",
      "Always noisy"
    ],
    "answer": 0
  },
  {
    "text": "What does Slow mean",
    "options": [
      "Not fast",
      "Very fast",
      "Very tired",
      "Very noisy"
    ],
    "answer": 0
  },
  {
    "text": "What does Small mean",
    "options": [
      "Not big",
      "Very big",
      "Very bright",
      "Very heavy"
    ],
    "answer": 0
  },
  {
    "text": "What does Soft mean",
    "options": [
      "Smooth and pleasant to touch",
      "Very hard",
      "Very loud",
      "Very fast"
    ],
    "answer": 0
  },
  {
    "text": "What does Strong mean",
    "options": [
      "Having great power",
      "Very weak",
      "Very tired",
      "Very slow"
    ],
    "answer": 0
  },
  {
    "text": "What does Tall mean",
    "options": [
      "High in height",
      "Very short",
      "Very wide",
      "Very fast"
    ],
    "answer": 0
  },
  {
    "text": "What does Warm mean",
    "options": [
      "Moderately hot",
      "Very cold",
      "Very fast",
      "Very loud"
    ],
    "answer": 0
  },
  {
    "text": "What does Wet mean",
    "options": [
      "Covered with water",
      "Very dry",
      "Very heavy",
      "Very dark"
    ],
    "answer": 0
  },
  {
    "text": "What does Wide mean",
    "options": [
      "Large from side to side",
      "Very narrow",
      "Very light",
      "Very hot"
    ],
    "answer": 0
  },
  {
    "text": "What does Young mean",
    "options": [
      "Not old",
      "Very tired",
      "Very heavy",
      "Very loud"
    ],
    "answer": 0
  }
]